mypackage/__init__.py
mypackage/main.py
bharmoria-0.0.1.dist-info/LICENSE
bharmoria-0.0.1.dist-info/METADATA
bharmoria-0.0.1.dist-info/WHEEL
bharmoria-0.0.1.dist-info/top_level.txt
bharmoria-0.0.1.dist-info/RECORD
